tenable_jira/__init__.py
tenable_jira/__main__.py
tenable_jira/cli.py
tenable_jira/config.py
tenable_jira/csv_ingestor.py
tenable_jira/my_cli.py
tenable_jira/scan_downloader.py
tenable_jira/transform.py
tenable_jira/utils.py
tenable_jira/jira/__init__.py
tenable_jira/jira/fields.py
tenable_jira/jira/issues.py
tenable_jira/jira/issuetypes.py
tenable_jira/jira/projects.py
tenable_jira/jira/screens.py
tenable_jira_cloud_mf-1.1.11.post5.dist-info/METADATA
tenable_jira_cloud_mf-1.1.11.post5.dist-info/WHEEL
tenable_jira_cloud_mf-1.1.11.post5.dist-info/entry_points.txt
tenable_jira_cloud_mf-1.1.11.post5.dist-info/top_level.txt
tenable_jira_cloud_mf-1.1.11.post5.dist-info/RECORD
