Metadata-Version: 2.1
Name: tenable-jira-cloud-mf
Version: 1.1.11.post5
Summary: Tenable -> Jira Cloud Bridge
Home-page: https://github.com/tenable/integrations-jira-cloud
Author: Tenable, Inc.
Author-email: smcgrath@tenable.com
License: MIT
Keywords: tenable tenable_io ibm jira
Platform: UNKNOWN
Classifier: Development Status :: 4 - Beta
Classifier: Intended Audience :: Information Technology
Classifier: Topic :: System :: Networking
Classifier: Topic :: Other/Nonlisted Topic
Classifier: License :: OSI Approved :: MIT License
Classifier: Programming Language :: Python :: 3.6
Classifier: Programming Language :: Python :: 3.7
Requires-Dist: pytenable (>=0.3.29)
Requires-Dist: restfly (>=1.1.0)
Requires-Dist: arrow (>=0.13.0)
Requires-Dist: Click (>=7.0)
Requires-Dist: pyyaml (>=5.1.2)
